vcf2fhir_test_517/__init__.py
vcf2fhir_test_517/common.py
vcf2fhir_test_517/converter.py
vcf2fhir_test_517/fhir_helper.py
vcf2fhir_test_517/gene_ref_seq.py
vcf2fhir_test_517/json_generator.py
vcf2fhir_test_517/test/__init__.py
vcf2fhir_test_517/test/test_integration.py
vcf2fhir_test_517/test/test_unit.py
vcf2fhir_test_517-0.0.17.dist-info/LICENSE
vcf2fhir_test_517-0.0.17.dist-info/METADATA
vcf2fhir_test_517-0.0.17.dist-info/WHEEL
vcf2fhir_test_517-0.0.17.dist-info/top_level.txt
vcf2fhir_test_517-0.0.17.dist-info/RECORD
