Metadata-Version: 2.1
Name: vcf2fhir-test-517
Version: 0.0.17
Summary: Convert .vcf files to HL7 FHIR standard
Home-page: https://github.com/Rohan-cod/vcf2fhir/tree/pep-517
Author: ""
Author-email: info@elimu.io
License: Apache Software License
Platform: UNKNOWN
Classifier: Programming Language :: Python :: 3
Classifier: Operating System :: OS Independent
Classifier: License :: OSI Approved :: Apache Software License
License-File: LICENSE
Requires-Dist: Cython (>=0.29.21)
Requires-Dist: fhirclient (==3.2.0)
Requires-Dist: pysam
Requires-Dist: pandas
Requires-Dist: pytz (>=2019.3)
Requires-Dist: pyVCF (>=0.6.8)
Requires-Dist: pyranges (>=0.0.96)
